etc/vc3/vc3-client.conf
vc3_client-2017.8.2.data/scripts/vc3-client
vc3_client-2017.8.2.dist-info/DESCRIPTION.rst
vc3_client-2017.8.2.dist-info/METADATA
vc3_client-2017.8.2.dist-info/RECORD
vc3_client-2017.8.2.dist-info/WHEEL
vc3_client-2017.8.2.dist-info/metadata.json
vc3_client-2017.8.2.dist-info/top_level.txt
vc3client/__init__.py
vc3client/__init__.pyo
vc3client/client.py
vc3client/client.pyo
vc3client/clientcli.py
vc3client/clientcli.pyo
vc3client/entities.py
vc3client/entities.pyo
