Metadata-Version: 2.0
Name: vc3-client
Version: 2017.8.2
Summary: vc3-client package
Home-page: http://virtualclusters.org/
Author: VC3 team
Author-email: vc3-project@googlegroups.com
License: GPL
Platform: UNKNOWN
Requires-Dist: cherrypy
Requires-Dist: pyopenssl
Requires-Dist: pyyaml
Requires-Dist: requests
Requires-Dist: vc3-info-service
